gcore/__init__.py
gcore/_base_client.py
gcore/_client.py
gcore/_compat.py
gcore/_constants.py
gcore/_exceptions.py
gcore/_files.py
gcore/_models.py
gcore/_qs.py
gcore/_resource.py
gcore/_response.py
gcore/_streaming.py
gcore/_types.py
gcore/_version.py
gcore/pagination.py
gcore/py.typed
gcore/_utils/__init__.py
gcore/_utils/_compat.py
gcore/_utils/_datetime_parse.py
gcore/_utils/_json.py
gcore/_utils/_logs.py
gcore/_utils/_proxy.py
gcore/_utils/_reflection.py
gcore/_utils/_resources_proxy.py
gcore/_utils/_streams.py
gcore/_utils/_sync.py
gcore/_utils/_transform.py
gcore/_utils/_typing.py
gcore/_utils/_utils.py
gcore/lib/.keep
gcore/lib/polling.py
gcore/resources/__init__.py
gcore/resources/cdn/__init__.py
gcore/resources/cdn/audit_logs.py
gcore/resources/cdn/cdn.py
gcore/resources/cdn/certificates.py
gcore/resources/cdn/ip_ranges.py
gcore/resources/cdn/logs.py
gcore/resources/cdn/metrics.py
gcore/resources/cdn/network_capacity.py
gcore/resources/cdn/origin_groups.py
gcore/resources/cdn/rule_templates.py
gcore/resources/cdn/shields.py
gcore/resources/cdn/statistics.py
gcore/resources/cdn/trusted_ca_certificates.py
gcore/resources/cdn/cdn_resources/__init__.py
gcore/resources/cdn/cdn_resources/cdn_resources.py
gcore/resources/cdn/cdn_resources/rules.py
gcore/resources/cdn/cdn_resources/shield.py
gcore/resources/cdn/logs_uploader/__init__.py
gcore/resources/cdn/logs_uploader/configs.py
gcore/resources/cdn/logs_uploader/logs_uploader.py
gcore/resources/cdn/logs_uploader/policies.py
gcore/resources/cdn/logs_uploader/targets.py
gcore/resources/cloud/__init__.py
gcore/resources/cloud/audit_logs.py
gcore/resources/cloud/billing_reservations.py
gcore/resources/cloud/cloud.py
gcore/resources/cloud/cost_reports.py
gcore/resources/cloud/floating_ips.py
gcore/resources/cloud/ip_ranges.py
gcore/resources/cloud/placement_groups.py
gcore/resources/cloud/projects.py
gcore/resources/cloud/regions.py
gcore/resources/cloud/secrets.py
gcore/resources/cloud/ssh_keys.py
gcore-0.31.0.dist-info/METADATA
gcore-0.31.0.dist-info/WHEEL
gcore-0.31.0.dist-info/licenses/LICENSE
gcore-0.31.0.dist-info/RECORD
